crowflow/__init__.py
crowflow/clustering/__init__.py
crowflow/clustering/repeated_stochastic_clustering.py
crowflow/feature_selection/__init__.py
crowflow/feature_selection/genetic_algorithm_fs.py
crowflow/optimization/__init__.py
crowflow/optimization/parameter_optimization.py
crowflow/plotting/__init__.py
crowflow/plotting/visualization_main.py
crowflow/robustness/__init__.py
crowflow/robustness/k_fold_validation.py
crowflow/robustness/pertubation_test.py
crowflow/utils/__init__.py
crowflow/utils/_private_helper_functions.py
crowflow-1.0.0.dist-info/LICENSE
crowflow-1.0.0.dist-info/METADATA
crowflow-1.0.0.dist-info/WHEEL
crowflow-1.0.0.dist-info/top_level.txt
crowflow-1.0.0.dist-info/RECORD
