Metadata-Version: 2.2
Name: crowflow
Version: 1.0.0
Summary: Python package for evaluating clustering stability through the use of repeated stochastic clustering and element-centric evaluation metrics.
Home-page: https://github.com/Core-Bioinformatics/crowflow-py
Author: Rafael Kollyfas
Author-email: rk720@cam.ac.uk
License: MIT
Keywords: clustering,evaluation,stability,assessment,machine learning
Requires-Python: >=3.7
License-File: LICENSE
Requires-Dist: numpy
Requires-Dist: matplotlib
Requires-Dist: scikit-learn
Requires-Dist: pandas
Requires-Dist: seaborn
Requires-Dist: plotnine
Requires-Dist: ClustAssessPy
Dynamic: author
Dynamic: author-email
Dynamic: description
Dynamic: description-content-type
Dynamic: home-page
Dynamic: keywords
Dynamic: license
Dynamic: requires-dist
Dynamic: requires-python
Dynamic: summary
